wledpy/__init__.py
wledpy/wled.py
wledpy_pctechjon-0.0.3.dist-info/LICENSE
wledpy_pctechjon-0.0.3.dist-info/METADATA
wledpy_pctechjon-0.0.3.dist-info/WHEEL
wledpy_pctechjon-0.0.3.dist-info/top_level.txt
wledpy_pctechjon-0.0.3.dist-info/RECORD
